trinsic_connect/__init__.py
trinsic_connect/api_client.py
trinsic_connect/api_response.py
trinsic_connect/configuration.py
trinsic_connect/exceptions.py
trinsic_connect/py.typed
trinsic_connect/rest.py
trinsic_connect/api/__init__.py
trinsic_connect/api/attachments_api.py
trinsic_connect/api/network_api.py
trinsic_connect/api/sessions_api.py
trinsic_connect/models/__init__.py
trinsic_connect/models/address.py
trinsic_connect/models/attachments.py
trinsic_connect/models/cancel_session_response.py
trinsic_connect/models/create_session_request.py
trinsic_connect/models/create_session_response.py
trinsic_connect/models/disclosed_fields.py
trinsic_connect/models/disclosed_fields_request.py
trinsic_connect/models/document_data.py
trinsic_connect/models/exchange_attachment_access_key_request.py
trinsic_connect/models/exchange_results_key_request.py
trinsic_connect/models/exchange_results_key_response.py
trinsic_connect/models/failure_message.py
trinsic_connect/models/get_session_response.py
trinsic_connect/models/identity_data.py
trinsic_connect/models/identity_lookup_response.py
trinsic_connect/models/list_providers_response.py
trinsic_connect/models/list_sessions_response.py
trinsic_connect/models/order_direction.py
trinsic_connect/models/person_data.py
trinsic_connect/models/provider_info.py
trinsic_connect/models/session.py
trinsic_connect/models/session_fail_code.py
trinsic_connect/models/session_ordering.py
trinsic_connect/models/session_state.py
trinsic_connect/models/validation_result.py
trinsic_connect/models/verification.py
trinsic_connect/models/verification_fail_code.py
Trinsic_Connect-0.2.3.dist-info/METADATA
Trinsic_Connect-0.2.3.dist-info/WHEEL
Trinsic_Connect-0.2.3.dist-info/top_level.txt
Trinsic_Connect-0.2.3.dist-info/RECORD
