Metadata-Version: 2.1
Name: Trinsic-Connect
Version: 0.2.3
Summary: Connect API
Home-page: https://trinsic.id
Author: OpenAPI Generator community
Author-email: team@openapitools.org
License: UNKNOWN
Keywords: OpenAPI,OpenAPI-Generator,Connect API
Platform: UNKNOWN
Requires-Dist: pydantic (>=2)
Requires-Dist: python-dateutil
Requires-Dist: typing-extensions (>=4.7.1)
Requires-Dist: urllib3 (<2.1.0,>=1.25.3)
